.gitattributes
.gitignore
.travis.yml
README.md
setup.py
sabapi/__init__.py
sabapi/api.py
sabapi/exceptions.py
sabapi/httpz.py
sabapi.egg-info/PKG-INFO
sabapi.egg-info/SOURCES.txt
sabapi.egg-info/dependency_links.txt
sabapi.egg-info/requires.txt
sabapi.egg-info/top_level.txt
tests/conftest.py
tests/test_integration.py